README.md
place_pictures.py
setup.py
ppdd.egg-info/PKG-INFO
ppdd.egg-info/SOURCES.txt
ppdd.egg-info/dependency_links.txt
ppdd.egg-info/entry_points.txt
ppdd.egg-info/requires.txt
ppdd.egg-info/top_level.txt