Metadata-Version: 1.0
Name: ppdd
Version: 0.1
Summary: Place pictures to directories based on date
Home-page: https://github.com/Sakaki/ppdd
Author: Sakaki Mirai
Author-email: oisiitakuwan@gmail.com
License: Apache License, Version 2.0
Platform: UNKNOWN
